Pandaspretty/__init__.py
Pandaspretty-1.1.0.dist-info/LICENSE.txt
Pandaspretty-1.1.0.dist-info/METADATA
Pandaspretty-1.1.0.dist-info/WHEEL
Pandaspretty-1.1.0.dist-info/top_level.txt
Pandaspretty-1.1.0.dist-info/RECORD
