Metadata-Version: 2.1
Name: Pandaspretty
Version: 1.1.0
Summary: Powerful package to prettify DataFrame into table.
Home-page: https://github.com/ayushkumarsingh2422005/PandasPretty
Author: Ayush Kumar Singh
Author-email: ayush2422005@gmail.com
License: MIT
Platform: UNKNOWN
License-File: LICENSE.txt
Requires-Dist: pandas
